setup.py
dabox/__init__.py
dabox/cv.py
dabox.egg-info/PKG-INFO
dabox.egg-info/SOURCES.txt
dabox.egg-info/dependency_links.txt
dabox.egg-info/requires.txt
dabox.egg-info/top_level.txt
dabox/sampling/__init__.py
dabox/sampling/bootstrap.py