Metadata-Version: 1.1
Name: dabox
Version: 0.0.2
Summary: Supplementary tools and functions for data analysis and ML
Home-page: https://github.com/tmullayanov/dabox
Author: Timur Mullayanov
Author-email: timur.r.mullayanov@gmail.com
License: MIT
Platform: UNKNOWN
Classifier: Operating System :: OS Independent
Classifier: Programming Language :: Python
Classifier: Programming Language :: Python :: 3
Classifier: Programming Language :: Python :: 2
Classifier: License :: OSI Approved :: MIT License
Classifier: Intended Audience :: Science/Research
Classifier: Topic :: Scientific/Engineering
Classifier: Development Status :: 2 - Pre-Alpha
